LICENSE
MANIFEST.in
README.md
setup.py
azamat/__init__.py
azamat/__version__.py
azamat/cli.py
azamat/core.py
azamat/exceptions.py
azamat/help.py
azamat/models.py
azamat/status_codes.py
azamat/utils.py
azamat.egg-info/PKG-INFO
azamat.egg-info/SOURCES.txt
azamat.egg-info/dependency_links.txt
azamat.egg-info/entry_points.txt
azamat.egg-info/not-zip-safe
azamat.egg-info/top_level.txt